tenrec/__init__.py
tenrec/__main__.py
tenrec/entrypoint.py
tenrec/installer.py
tenrec/server.py
tenrec/sessions.py
tenrec/documentation/__init__.py
tenrec/documentation/formatter.py
tenrec/documentation/generator.py
tenrec/documentation/static/README.md
tenrec/documentation/static/index.html
tenrec/documentation/static/_media/darn-mice-solve.mp4
tenrec/documentation/static/_media/icon.png
tenrec/documentation/static/_media/icon.svg
tenrec/management/__init__.py
tenrec/management/config.py
tenrec/management/environment.py
tenrec/management/options.py
tenrec/management/utils.py
tenrec/management/venv.py
tenrec/plugins/__init__.py
tenrec/plugins/database_manager.py
tenrec/plugins/plugin_loader.py
tenrec/plugins/plugin_manager.py
tenrec/plugins/models/__init__.py
tenrec/plugins/models/base.py
tenrec/plugins/models/exceptions.py
tenrec/plugins/models/ida.py
tenrec/plugins/models/operation.py
tenrec/plugins/models/parameters.py
tenrec/plugins/plugins/__init__.py
tenrec/plugins/plugins/bytes.py
tenrec/plugins/plugins/comments.py
tenrec/plugins/plugins/entries.py
tenrec/plugins/plugins/functions.py
tenrec/plugins/plugins/names.py
tenrec/plugins/plugins/segments.py
tenrec/plugins/plugins/strings.py
tenrec/plugins/plugins/types.py
tenrec/plugins/plugins/utils.py
tenrec/plugins/plugins/xrefs.py
tenrec-1.0.0.dist-info/METADATA
tenrec-1.0.0.dist-info/WHEEL
tenrec-1.0.0.dist-info/entry_points.txt
tenrec-1.0.0.dist-info/licenses/LICENSE
tenrec-1.0.0.dist-info/RECORD
