Metadata-Version: 2.4
Name: tenrec
Version: 1.0.0
Summary: A modern MCP server implementation for IDA Pro using ida-domain and FastMCP.
Author: Axel Mierczuk
License: MIT
License-File: LICENSE
Classifier: Development Status :: 5 - Production/Stable
Classifier: Intended Audience :: Developers
Classifier: Operating System :: MacOS
Classifier: Operating System :: Microsoft :: Windows
Classifier: Programming Language :: Python :: 3
Classifier: Programming Language :: Python :: 3.10
Requires-Python: >=3.10
Requires-Dist: fastmcp>=2.12.3
Requires-Dist: gitpython>=3.1.45
Requires-Dist: giturlparse>=0.12.0
Requires-Dist: gunicorn>=23.0.0
Requires-Dist: ida-domain==0.2.0
Requires-Dist: jinja2>=3.1.6
Requires-Dist: loguru>=0.7.3
Requires-Dist: rich-click>=1.8.9
Requires-Dist: setuptools>=61.0
Requires-Dist: termcolor>=3.1.0
